ZhihuWendaQinshouBaYijiaGongsiNongkuaShiZenyangDeGanjue/README.md
ZhihuWendaQinshouBaYijiaGongsiNongkuaShiZenyangDeGanjue/__init__.py
ZhihuWendaQinshouBaYijiaGongsiNongkuaShiZenyangDeGanjue/__main__.py
ZhihuWendaQinshouBaYijiaGongsiNongkuaShiZenyangDeGanjue/file.epub
ZhihuWendaQinshouBaYijiaGongsiNongkuaShiZenyangDeGanjue/index.html
ZhihuWendaQinshouBaYijiaGongsiNongkuaShiZenyangDeGanjue/css/__init__.py
ZhihuWendaQinshouBaYijiaGongsiNongkuaShiZenyangDeGanjue/css/annotations.css
ZhihuWendaQinshouBaYijiaGongsiNongkuaShiZenyangDeGanjue/css/main.css
ZhihuWendaQinshouBaYijiaGongsiNongkuaShiZenyangDeGanjue/css/normalize.css
ZhihuWendaQinshouBaYijiaGongsiNongkuaShiZenyangDeGanjue/css/popup.css
ZhihuWendaQinshouBaYijiaGongsiNongkuaShiZenyangDeGanjue/font/__init__.py
ZhihuWendaQinshouBaYijiaGongsiNongkuaShiZenyangDeGanjue/font/fontello.eot
ZhihuWendaQinshouBaYijiaGongsiNongkuaShiZenyangDeGanjue/font/fontello.svg
ZhihuWendaQinshouBaYijiaGongsiNongkuaShiZenyangDeGanjue/font/fontello.ttf
ZhihuWendaQinshouBaYijiaGongsiNongkuaShiZenyangDeGanjue/font/fontello.woff
ZhihuWendaQinshouBaYijiaGongsiNongkuaShiZenyangDeGanjue/img/__init__.py
ZhihuWendaQinshouBaYijiaGongsiNongkuaShiZenyangDeGanjue/img/annotator-glyph-sprite.png
ZhihuWendaQinshouBaYijiaGongsiNongkuaShiZenyangDeGanjue/img/annotator-icon-sprite.png
ZhihuWendaQinshouBaYijiaGongsiNongkuaShiZenyangDeGanjue/img/apple-touch-icon.png
ZhihuWendaQinshouBaYijiaGongsiNongkuaShiZenyangDeGanjue/img/cancelfullscreen.png
ZhihuWendaQinshouBaYijiaGongsiNongkuaShiZenyangDeGanjue/img/close.png
ZhihuWendaQinshouBaYijiaGongsiNongkuaShiZenyangDeGanjue/img/fullscreen.png
ZhihuWendaQinshouBaYijiaGongsiNongkuaShiZenyangDeGanjue/img/loader.gif
ZhihuWendaQinshouBaYijiaGongsiNongkuaShiZenyangDeGanjue/img/menu-icon.png
ZhihuWendaQinshouBaYijiaGongsiNongkuaShiZenyangDeGanjue/img/save.png
ZhihuWendaQinshouBaYijiaGongsiNongkuaShiZenyangDeGanjue/img/saved.png
ZhihuWendaQinshouBaYijiaGongsiNongkuaShiZenyangDeGanjue/img/settings-s.png
zhihu_wenda_qinshou_ba_yijia_gongsi_nongkua_shi_zenyang_de_ganjue-2024.3.5.0.dist-info/METADATA
zhihu_wenda_qinshou_ba_yijia_gongsi_nongkua_shi_zenyang_de_ganjue-2024.3.5.0.dist-info/WHEEL
zhihu_wenda_qinshou_ba_yijia_gongsi_nongkua_shi_zenyang_de_ganjue-2024.3.5.0.dist-info/entry_points.txt
zhihu_wenda_qinshou_ba_yijia_gongsi_nongkua_shi_zenyang_de_ganjue-2024.3.5.0.dist-info/top_level.txt
zhihu_wenda_qinshou_ba_yijia_gongsi_nongkua_shi_zenyang_de_ganjue-2024.3.5.0.dist-info/RECORD
